mailman_public_inbox/__init__.py
mailman_public_inbox-0.1.0.dist-info/LICENCE.txt
mailman_public_inbox-0.1.0.dist-info/METADATA
mailman_public_inbox-0.1.0.dist-info/WHEEL
mailman_public_inbox-0.1.0.dist-info/top_level.txt
mailman_public_inbox-0.1.0.dist-info/RECORD
