Metadata-Version: 2.1
Name: mailman-public-inbox
Version: 0.1.0
Summary: Mailman archiver plugin for Public Inbox
Home-page: https://github.com/tohojo/mailman-public-inbox/
Author: Toke Høiland-Jørgensen
Author-email: toke@toke.dk
License: GPLv3
Keywords: email
Platform: UNKNOWN
Classifier: Development Status :: 4 - Beta
Classifier: License :: OSI Approved :: GNU General Public License v3 (GPLv3)
Classifier: Topic :: Communications :: Email :: Mailing List Servers
Classifier: Programming Language :: Python :: 3
Requires-Dist: setuptools
Requires-Dist: mailman
Requires-Dist: zope.interface
